asn_viewer/__init__.py
asn_viewer/__main__.py
asn_viewer/asn_decoder.py
asn_viewer/asn_viewer_config.py
asn_viewer/runapp.py
asn_viewer-0.0.4.dist-info/LICENSE
asn_viewer-0.0.4.dist-info/METADATA
asn_viewer-0.0.4.dist-info/WHEEL
asn_viewer-0.0.4.dist-info/entry_points.txt
asn_viewer-0.0.4.dist-info/top_level.txt
asn_viewer-0.0.4.dist-info/RECORD
