Metadata-Version: 2.1
Name: asn_viewer
Version: 0.0.4
Summary: ASN decoder and viewer
Home-page: https://gitlab.com/sergwy/asn-viewer
Maintainer: Sergey Yakimov
Maintainer-email: sergwy@gmail.com
License: Copyright 2024 Sergey Yakimov sergwy@gmail.com
License-File: LICENSE
Requires-Dist: PyYAML
Requires-Dist: asn1tools
